server/__main__.py
mcp_discovery-0.1.6.dist-info/METADATA
mcp_discovery-0.1.6.dist-info/WHEEL
mcp_discovery-0.1.6.dist-info/entry_points.txt
mcp_discovery-0.1.6.dist-info/top_level.txt
mcp_discovery-0.1.6.dist-info/RECORD
