Metadata-Version: 2.4
Name: mcp-discovery
Version: 0.1.6
Summary: MCP for watson discovery
Requires-Python: >=3.10
Requires-Dist: asyncio>=3.4.3
Requires-Dist: httpx>=0.28.1
Requires-Dist: ibm-watson>=9.0.0
Requires-Dist: mcp[cli]>=1.4.1
